argel1200/__init__.py
argel1200/LICENSE.txt
argel1200/README.rst
argel1200/utilities/__init__.py
argel1200/utilities/click.py
argel1200/utilities/dumper.py
argel1200/utilities/utilities.py
argel1200-1.3.3.dist-info/METADATA
argel1200-1.3.3.dist-info/WHEEL
argel1200-1.3.3.dist-info/RECORD
