Metadata-Version: 2.4
Name: argel1200
Version: 1.3.3
Summary: My utility functions
License: MIT
Author: argel1200
Author-email: argel@msn.com
Requires-Python: >=3.9,<4.0
Classifier: License :: OSI Approved :: MIT License
Classifier: Programming Language :: Python :: 3
Classifier: Programming Language :: Python :: 3.9
Classifier: Programming Language :: Python :: 3.10
Classifier: Programming Language :: Python :: 3.11
Classifier: Programming Language :: Python :: 3.12
Classifier: Programming Language :: Python :: 3.13
Classifier: Programming Language :: Python :: 3.14
Requires-Dist: Dumper (>0.10.2)
Requires-Dist: click (>7.1.2)
Project-URL: Homepage, https://github.com/argel1200/argel1200-python
